cau/Timetable.py
cau/__init__.py
cau/timetable-cli.py
cau_services-0.0.3.dist-info/LICENSE
cau_services-0.0.3.dist-info/METADATA
cau_services-0.0.3.dist-info/WHEEL
cau_services-0.0.3.dist-info/top_level.txt
cau_services-0.0.3.dist-info/RECORD
