Metadata-Version: 2.1
Name: cau_services
Version: 0.0.3
Summary: CAU (Central Asian University) Services Python Client, for student projects
Author-email: Timur Urunbaev <urunbaev.timur@gmail.com>
License: # Released under MIT License
Classifier: Programming Language :: Python :: 3
Classifier: License :: OSI Approved :: MIT License
Classifier: Operating System :: POSIX
Requires-Python: >=3.10
License-File: LICENSE
Requires-Dist: pandas
Requires-Dist: tqdm
Requires-Dist: requests
Requires-Dist: importlib-metadata ; python_version < "3.12"
